numpyro_schechter/__init__.py
numpyro_schechter/distribution.py
numpyro_schechter/math_utils.py
numpyro_schechter-1.1.0.dist-info/LICENSE
numpyro_schechter-1.1.0.dist-info/METADATA
numpyro_schechter-1.1.0.dist-info/WHEEL
numpyro_schechter-1.1.0.dist-info/RECORD
