Metadata-Version: 2.3
Name: numpyro_schechter
Version: 1.1.0
Summary: Schechter galaxy luminosity distribution for NumPyro.
License: MIT
Keywords: numpyro,schechter,astronomy,bayesian,distribution
Author: Alice Serene
Author-email: aserene@swin.edu.au
Requires-Python: >=3.10,<3.14
Classifier: License :: OSI Approved :: MIT License
Classifier: Operating System :: OS Independent
Classifier: Programming Language :: Python :: 3
Classifier: Programming Language :: Python :: 3.10
Classifier: Programming Language :: Python :: 3.11
Classifier: Programming Language :: Python :: 3.12
Classifier: Programming Language :: Python :: 3.13
Requires-Dist: jax (>=0.4.25)
Requires-Dist: jaxlib (>=0.4.25)
Requires-Dist: numpy (>=1.26,<2.0)
Requires-Dist: numpyro (>=0.13.2)
Requires-Dist: scipy (>=1.13,<1.15)
Project-URL: Homepage, https://github.com/alserene/numpyro_schechter
Project-URL: Issues, https://github.com/alserene/numpyro_schechter/issues
